graph_package/__init__.py
graph_package/fake_news_detection.py
graph_package/gnn_xa.py
graph_package/tabular_to_graph.py
graph_package/traffic_prediction.py
graph_package/gnn_project/__init__.py
graph_package/gnn_project/config.py
graph_package/gnn_project/dashboard.py
graph_package/gnn_project/dataset.py
graph_package/gnn_project/dataset_featurizer.py
graph_package/gnn_project/model.py
graph_package/gnn_project/oversample_data.py
graph_package/gnn_project/predict.py
graph_package/gnn_project/train.py
graph_package/gnn_project/utils.py
graph_package/gvae/__init__.py
graph_package/gvae/config.py
graph_package/gvae/dataset.py
graph_package/gvae/gvae.py
graph_package/gvae/train.py
graph_package/gvae/utils.py
graph_package-0.0.1.dist-info/LICENSE
graph_package-0.0.1.dist-info/METADATA
graph_package-0.0.1.dist-info/WHEEL
graph_package-0.0.1.dist-info/top_level.txt
graph_package-0.0.1.dist-info/RECORD
