Metadata-Version: 2.1
Name: Graph-Package
Version: 0.0.1
Summary: For Graph Neural Network
Home-page: https://github.com/jamescalam/aesthetic_ascii
Author: Binary Brains
Classifier: Programming Language :: Python :: 3
Classifier: License :: OSI Approved :: MIT License
Classifier: Operating System :: OS Independent
Requires-Python: >=3.7
License-File: LICENSE
